{
  "player_build_data": [
    {
      "type": "playerBuildTimingData",
      "msg": {
        "build_event_id": "c4ef92276505bc9c982a9ef082820cd6",
        "build_player": 12337,
        "preprocess_player": 80,
        "produce_player_script_assemblies": 5120,
        "build_scripts_dlls": 18,
        "writing_asset_files": 1256,
        "postprocess_built_player": 4414,
        "node_summary_table": [
          {
            "name": "Csc",
            "duration": 1977
          },
          {
            "name": "UnityLinker.exe",
            "duration": 201
          }
        ]
      },
      "version": 1
    },
    {
      "type": "unityLinkerData",
      "msg": {
        "build_event_id": "c4ef92276505bc9c982a9ef082820cd6",
        "node_executed": true,
        "option_rule_set": "Copy"
      },
      "version": 1
    }
  ]
}